MANIFEST.in
README.md
distribute_setup.py
dotenv
setup.py
dotenv/__init__.py
dotenv/__main__.py
dotenv.egg-info/PKG-INFO
dotenv.egg-info/SOURCES.txt
dotenv.egg-info/dependency_links.txt
dotenv.egg-info/top_level.txt
scripts/dotenv