Metadata-Version: 1.0
Name: dotenv
Version: 0.0.1
Summary: Handle .env files
Home-page: http://witoi.github.com
Author: Pedro Burón
Author-email: pedro@witoi.com
License: UNKNOWN
Platform: UNKNOWN
